{
    "##": "Legacy version of JGRPP",
    "version": "0.13.2",
    "description": "JGRPP 0.13.2 legacy version",
    "homepage": "https://github.com/JGRennison/OpenTTD-patches",
    "license": "GPL-2.0-or-later",
    "notes": [
        "This install does not come with graphics, sounds or music.",
        "You may want to download the items from the OpenTTD website.",
        "If you have any problems with the installed version, please consider reinstalling the game."
    ],
    "architecture": {
        "64bit": {
            "url": "https://github.com/JGRennison/OpenTTD-patches/releases/download/jgrpp-0.13.2/openttd-custom-jgrpp-0.13.2-MINGW-win64.zip",
            "hash": "1ea440ec09e9dc4361c9b99e4d6157f9b90656903e250aed0941642243bc51dd"
        },
        "32bit": {
            "url": "https://github.com/JGRennison/OpenTTD-patches/releases/download/jgrpp-0.13.2/openttd-custom-jgrpp-0.13.2-MINGW-win32.zip",
            "hash": "b05e9cf6e75635fb1faf71ff64729a007df628bc35bf9e40da4fc6442e68135c"
        }
    },
    "bin": "openttd.exe",
    "shortcuts": [
        [
            "openttd.exe",
            "OpenTTD-JGRPP [0.13.2]"
        ]
    ]
}
